Metadata-Version: 2.1
Name: xfce4-terminal-themes
Version: 0.1
Summary: Manage your xfce4-terminal themes with ease!
Home-page: https://github.com/jcmuller/xfce4-terminal-themes
Author: Juan C. Müller
Author-email: jcmuller@gmail.com
License: UNKNOWN
Platform: UNKNOWN
Classifier: Development Status :: 3 - Alpha
Classifier: Intended Audience :: Information Technology
Classifier: License :: OSI Approved :: MIT License
Classifier: Operating System :: OS Independent
Classifier: Programming Language :: Python :: 2.7
Classifier: Programming Language :: Python :: 3.7
Classifier: Topic :: Terminals
